{
    "wallpaper": "/home/nizar/Downloads/TRYTHIS.jpg",
    "alpha": "100",
    "special": {
        "background": "#090117",
        "foreground": "#8ac2d4",
        "cursor": "#8ac2d4"
    },
    "colors": {
        "color0": "#090117",
        "color1": "#F20415",
        "color2": "#B51342",
        "color3": "#F5C45C",
        "color4": "#122397",
        "color5": "#055F9F",
        "color6": "#334CCF",
        "color7": "#8ac2d4",
        "color8": "#608794",
        "color9": "#F20415",
        "color10": "#B51342",
        "color11": "#F5C45C",
        "color12": "#122397",
        "color13": "#055F9F",
        "color14": "#334CCF",
        "color15": "#8ac2d4"
    }
}