{
    "wallpaper": "/home/nizar/wallpapers/wallpaper42.jpg",
    "alpha": "100",
    "special": {
        "background": "#192d2f",
        "foreground": "#def2f0",
        "cursor": "#def2f0"
    },
    "colors": {
        "color0": "#192d2f",
        "color1": "#9AACAA",
        "color2": "#EFADA0",
        "color3": "#A8D8A6",
        "color4": "#E1E7AE",
        "color5": "#AAE9E4",
        "color6": "#E9E2D3",
        "color7": "#def2f0",
        "color8": "#9ba9a8",
        "color9": "#9AACAA",
        "color10": "#EFADA0",
        "color11": "#A8D8A6",
        "color12": "#E1E7AE",
        "color13": "#AAE9E4",
        "color14": "#E9E2D3",
        "color15": "#def2f0"
    }
}